tflump/__init__.py
tflump/client.py
tflump/config.py
tflump/stores.py
tflump/data/lines-bus.json
tflump/data/lines-bus.pkl
tflump/data/lines-bus.pkl.bak
tflump/data/stoppoints.json
tflump/data/stoppoints.pkl
tflump/data/stoppoints.pkl.bak
tflump/models/__init__.py
tflump/models/line.py
tflump/models/route.py
tflump/models/shared.py
tflump/models/stoppoint.py
tflump-0.1.3.dist-info/METADATA
tflump-0.1.3.dist-info/WHEEL
tflump-0.1.3.dist-info/licenses/LICENSE
tflump-0.1.3.dist-info/RECORD
