Metadata-Version: 2.3
Name: tflump
Version: 0.1.3
Summary: TfL API access and analysis in python
Project-URL: homepage, https://pilchard.github.io/tflump/
Project-URL: documentation, https://pilchard.github.io/tflump/
Project-URL: repository, https://github.com/pilchard/tflump
Author-email: pilchard <187820+pilchard@users.noreply.github.com>
License: MIT
License-File: LICENSE
Classifier: Programming Language :: Python :: 3
Requires-Python: >=3.8
Requires-Dist: httpx>=0.27.0
Requires-Dist: pandas>=2.2.2
Requires-Dist: pydantic-settings>=2.3.4
Requires-Dist: pydantic>=2.8.2
Requires-Dist: python-dotenv>=1.0.1
Provides-Extra: dev
